varcache/__init__.py
varcache-0.2.0.dist-info/METADATA
varcache-0.2.0.dist-info/WHEEL
varcache-0.2.0.dist-info/top_level.txt
varcache-0.2.0.dist-info/RECORD
