Metadata-Version: 2.4
Name: varcache
Version: 0.2.0
Summary: Simple file-based cache for Python objects.
Home-page: https://github.com/fomalhaut88/varcache
Author: Alexander Khlebushchev
License: MIT
Project-URL: Homepage, https://pypi.org/project/varcache/
Project-URL: Documentation, https://fomalhaut88.github.io/varcache/
Project-URL: Source, https://github.com/fomalhaut88/varcache
Project-URL: Issues, https://github.com/fomalhaut88/varcache/issues
Classifier: Development Status :: 5 - Production/Stable
Classifier: Intended Audience :: Developers
Classifier: Topic :: Software Development :: Libraries :: Python Modules
Classifier: Programming Language :: Python :: 3.12
Classifier: Operating System :: OS Independent
Requires-Python: >=3.12
Dynamic: author
Dynamic: classifier
Dynamic: description
Dynamic: description-content-type
Dynamic: home-page
Dynamic: license
Dynamic: project-url
Dynamic: requires-python
Dynamic: summary
